enmerkar_underscore/__init__.py
enmerkar_underscore/vendor/__init__.py
enmerkar_underscore/vendor/markey/__init__.py
enmerkar_underscore/vendor/markey/_compat.py
enmerkar_underscore/vendor/markey/machine.py
enmerkar_underscore/vendor/markey/rules.py
enmerkar_underscore/vendor/markey/tools.py
enmerkar_underscore/vendor/markey/underscore.py
enmerkar_underscore/vendor/markey/tests/__init__.py
enmerkar_underscore/vendor/markey/tests/test_machine.py
enmerkar_underscore/vendor/markey/tests/test_rules.py
enmerkar_underscore/vendor/markey/tests/test_tools.py
enmerkar_underscore-2.4.0.dist-info/licenses/LICENSE
enmerkar_underscore-2.4.0.dist-info/METADATA
enmerkar_underscore-2.4.0.dist-info/WHEEL
enmerkar_underscore-2.4.0.dist-info/entry_points.txt
enmerkar_underscore-2.4.0.dist-info/top_level.txt
enmerkar_underscore-2.4.0.dist-info/RECORD
