Metadata-Version: 2.4
Name: enmerkar-underscore
Version: 2.4.0
Summary: Implements a underscore extractor for django-babel.
Home-page: https://github.com/openedx/enmerkar-underscore
Author: edX
Author-email: oscm@edx.org
License: BSD
Keywords: enmerkar-underscore
Classifier: Development Status :: 5 - Production/Stable
Classifier: Intended Audience :: Developers
Classifier: License :: OSI Approved :: BSD License
Classifier: Natural Language :: English
Classifier: Programming Language :: Python
Classifier: Programming Language :: Python :: 3
Classifier: Programming Language :: Python :: 3.11
Classifier: Programming Language :: Python :: 3.12
Classifier: Framework :: Django
Classifier: Framework :: Django :: 4.2
Classifier: Framework :: Django :: 5.2
License-File: LICENSE
Requires-Dist: babel>=1.3
Requires-Dist: django
Requires-Dist: enmerkar==0.7.1
Dynamic: author
Dynamic: author-email
Dynamic: classifier
Dynamic: description
Dynamic: home-page
Dynamic: keywords
Dynamic: license
Dynamic: license-file
Dynamic: requires-dist
Dynamic: summary
